{"source":{"publisher":"BlockSense.One","client":"Chaince Exchange","description":"Chaince Token Data for all EOS pairs","limitations":{"delay":"15 seconds","rate":"unlimited"},"time_zone":"UTC","timestamp":1546052093,"created_at":"12/29/2018 02:54:53 AM UTC"},"EOS":{"eos_price":"2.60","usd_price":"2.67","percent_change":"16.07","24_hour_volume":"228056.51","24_hour_volume_in_eos":592946.926,"24_hour_volume_in_usd":608910.8817},"CET":{"eos_price":"0.0030","usd_price":"0.0081","percent_change":"0.00","24_hour_volume":"2638017.3","24_hour_volume_in_eos":7914.0519,"24_hour_volume_in_usd":21367.94013},"TPT":{"eos_price":"0.000791","usd_price":"0.0021","percent_change":"-3.06","24_hour_volume":"8020385.6","24_hour_volume_in_eos":6344.1250096,"24_hour_volume_in_usd":16842.80976},"TOOK":{"eos_price":"0.00290","usd_price":"0.0078","percent_change":"-0.34","24_hour_volume":"2363256.3","24_hour_volume_in_eos":6853.44327,"24_hour_volume_in_usd":18433.39914},"UCTT":{"eos_price":"0.000947","usd_price":"0.0026","percent_change":"0.96","24_hour_volume":"6618803.2","24_hour_volume_in_eos":6268.0066304,"24_hour_volume_in_usd":17208.88832},"PUB":{"eos_price":"0.00183","usd_price":"0.0049","percent_change":"1.67","24_hour_volume":"3373464.7","24_hour_volume_in_eos":6173.440401,"24_hour_volume_in_usd":16529.97703},"CHL":{"eos_price":"0.0000473","usd_price":"0.0001","percent_change":"25.80","24_hour_volume":"653562.8","24_hour_volume_in_eos":30.91352044,"24_hour_volume_in_usd":65.35628},"WBI":{"eos_price":"0.0092","usd_price":"0.025","percent_change":"27.78","24_hour_volume":"457873.72","24_hour_volume_in_eos":4212.438224,"24_hour_volume_in_usd":11446.843},"IQ":{"eos_price":"0.00103","usd_price":"0.0028","percent_change":"-4.63","24_hour_volume":"2963605.4","24_hour_volume_in_eos":3052.513562,"24_hour_volume_in_usd":8298.09512},"HORUS":{"eos_price":"0.00177","usd_price":"0.0048","percent_change":"4.12","24_hour_volume":"703185.3","24_hour_volume_in_eos":1244.637981,"24_hour_volume_in_usd":3375.28944},"KARMA":{"eos_price":"0.000260","usd_price":"0.0007","percent_change":"-3.70","24_hour_volume":"4087996.2","24_hour_volume_in_eos":1062.879012,"24_hour_volume_in_usd":2861.59734},"TRYBE":{"eos_price":"0.00238","usd_price":"0.0064","percent_change":"22.05","24_hour_volume":"273920.7","24_hour_volume_in_eos":651.931266,"24_hour_volume_in_usd":1753.09248},"INF":{"eos_price":"0.00115","usd_price":"0.0031","percent_change":"12.75","24_hour_volume":"366944.8","24_hour_volume_in_eos":421.98652,"24_hour_volume_in_usd":1137.52888},"ADE":{"eos_price":"0.000170","usd_price":"0.0005","percent_change":"0.00","24_hour_volume":"772685.7","24_hour_volume_in_eos":131.356569,"24_hour_volume_in_usd":386.34285},"OCT":{"eos_price":"0.0207","usd_price":"0.056","percent_change":"-7.17","24_hour_volume":"54060.95","24_hour_volume_in_eos":1119.061665,"24_hour_volume_in_usd":3027.4132},"BNT":{"eos_price":"0.2430","usd_price":"0.66","percent_change":"5.65","24_hour_volume":"4289.371","24_hour_volume_in_eos":1042.317153,"24_hour_volume_in_usd":2830.98486},"MEETONE":{"eos_price":"0.00045","usd_price":"0.0012","percent_change":"0.00","24_hour_volume":"4419833.4","24_hour_volume_in_eos":1988.92503,"24_hour_volume_in_usd":5303.80008},"EOSISH":{"eos_price":"0.00098","usd_price":"0.0026","percent_change":"-2.00","24_hour_volume":"386482.3","24_hour_volume_in_eos":378.752654,"24_hour_volume_in_usd":1004.85398},"BOID":{"eos_price":"0.0000900","usd_price":"0.0002","percent_change":"0.00","24_hour_volume":"2384047.9","24_hour_volume_in_eos":214.564311,"24_hour_volume_in_usd":476.80958},"ZKS":{"eos_price":"0.000155","usd_price":"0.0004","percent_change":"-0.64","24_hour_volume":"1068326.6","24_hour_volume_in_eos":165.590623,"24_hour_volume_in_usd":427.33064},"HVT":{"eos_price":"0.00082","usd_price":"0.0022","percent_change":"-2.38","24_hour_volume":"437402.4","24_hour_volume_in_eos":358.669968,"24_hour_volume_in_usd":962.28528},"ECASH":{"eos_price":"0.00690","usd_price":"0.019","percent_change":"2.99","24_hour_volume":"254747.1","24_hour_volume_in_eos":1757.75499,"24_hour_volume_in_usd":4840.1949},"ATD":{"eos_price":"0.000055","usd_price":"0.0001","percent_change":"-8.33","24_hour_volume":"1760975.3","24_hour_volume_in_eos":96.8536415,"24_hour_volume_in_usd":176.09753},"ARN":{"eos_price":"0.1300","usd_price":"0.35","percent_change":"-6.47","24_hour_volume":"2232.741","24_hour_volume_in_eos":290.25633,"24_hour_volume_in_usd":781.45935},"WECASH":{"eos_price":"0.0000270","usd_price":"0.0001","percent_change":"-10.00","24_hour_volume":"2018102.8","24_hour_volume_in_eos":54.4887756,"24_hour_volume_in_usd":201.81028},"EUSD":{"eos_price":"0.400","usd_price":"1.08","percent_change":"0.00","24_hour_volume":"2365.469","24_hour_volume_in_eos":946.1876,"24_hour_volume_in_usd":2554.70652},"EETH":{"eos_price":"50.0","usd_price":"134.88","percent_change":"0.00","24_hour_volume":"17.76505","24_hour_volume_in_eos":888.2525,"24_hour_volume_in_usd":2396.149944},"EBTC":{"eos_price":"1500.0","usd_price":"4046.40","percent_change":"2.04","24_hour_volume":"0.588824","24_hour_volume_in_eos":883.236,"24_hour_volume_in_usd":2382.6174336},"RAM":{"eos_price":"0.0610","usd_price":"0.16","percent_change":"0.00","24_hour_volume":"100.000","24_hour_volume_in_eos":6.1,"24_hour_volume_in_usd":16},"BTC":{"eos_price":"1500.0","usd_price":"4046.40","percent_change":"-3.85","24_hour_volume":"5.564254","24_hour_volume_in_eos":8346.381,"24_hour_volume_in_usd":22515.1973856},"ETH":{"eos_price":"50.0","usd_price":"134.88","percent_change":"13.64","24_hour_volume":"58.75317","24_hour_volume_in_eos":2937.6585,"24_hour_volume_in_usd":7924.6275696},"EOSDAC":{"usd_price":"0.0065","eos_price":"0.00245","percent_change":"7.83","24_hour_volume":"91321.42286685","24_hour_volume_in_eos":223.73748602378,"24_hour_volume_in_usd":593.86960540273}}